debauto/__init__.py
debauto/bancos/bb.py
debauto/bancos/caixa.py
debauto/bancos/santander.py
debauto/remessa.py
debauto/retorno.py
debauto/utils.py
debauto-0.2.3.dist-info/LICENSE.md
debauto-0.2.3.dist-info/WHEEL
debauto-0.2.3.dist-info/METADATA
debauto-0.2.3.dist-info/RECORD
