Metadata-Version: 2.1
Name: debauto
Version: 0.2.3
Summary: Criação de remessas de débito automático no formato CNAB 150 da Febraban.
Author: Flavio Milan
Author-email: oflaviomilan@gmail.com
Requires-Python: >=3.5,<4.0
Classifier: Programming Language :: Python :: 3
Classifier: Programming Language :: Python :: 3.5
Classifier: Programming Language :: Python :: 3.6
Classifier: Programming Language :: Python :: 3.7
Classifier: Programming Language :: Python :: 3.8
